HISTORY.md
LICENSE.txt
MANIFEST.in
README.md
USAGE.md
setup.py
tox.ini
libgreader/__init__.py
libgreader/auth.py
libgreader/googlereader.py
libgreader/items.py
libgreader/url.py
libgreader.egg-info/PKG-INFO
libgreader.egg-info/SOURCES.txt
libgreader.egg-info/dependency_links.txt
libgreader.egg-info/requires.txt
libgreader.egg-info/top_level.txt
tests/__init__.py
tests/test_auth.py
tests/test_special_feeds.py