Metadata-Version: 1.1
Name: libgreader
Version: 0.7.1
Summary: Library for working with the Google Reader API
Home-page: https://github.com/askedrelic/libgreader
Author: Matt Behrens <askedrelic@gmail.com>
Author-email: askedrelic@gmail.com
License: The MIT License (MIT)
